{
    "blocks": [
        {"part": 1,
         "type": "instruction",
         "file": ".\\instructions\\baseline.json"
        },
        {"part": 2,
         "type": "set",
         "file": ".\\configs\\sets\\noise_of_letters_2.json"
        },
        {"part": 3,
         "type": "set",
         "file": ".\\configs\\sets\\noise_of_shapes_1.json"
        },
        {"part": 4,
         "type": "instruction",
         "file": ".\\instructions\\short_break.json"
        },
        {"part": 5,
         "type": "set",
         "file": ".\\configs\\sets\\noise_of_letters_1.json"
        },
        {"part": 6,
         "type": "set",
         "file": ".\\configs\\sets\\noise_of_shapes_2.json"
        },
        {"part": 7,
         "type": "instruction",
         "file": ".\\instructions\\end.json"
        }
    ]
}